{
    "series": [
        {
            "number": 0,
            "real": 453.62899999999996,
            "imag": 610.5650000000036
        },
        {
            "number": 1,
            "real": -78.55295146985048,
            "imag": -217.72149583232436
        },
        {
            "number": -1,
            "real": -25.550916839266538,
            "imag": -44.67561628637871
        },
        {
            "number": 2,
            "real": -61.25839472996029,
            "imag": -51.8136550646894
        },
        {
            "number": -2,
            "real": 2.6951116168176563,
            "imag": -116.25128206636235
        },
        {
            "number": 3,
            "real": -28.007463812669354,
            "imag": 51.184308990096746
        },
        {
            "number": -3,
            "real": 6.2531108107747775,
            "imag": -14.786436814814175
        },
        {
            "number": 4,
            "real": -3.957355543625302,
            "imag": 6.026970968390525
        },
        {
            "number": -4,
            "real": -4.0369288263368395,
            "imag": 6.0269709683902954
        },
        {
            "number": 5,
            "real": 2.294350820205752,
            "imag": -5.428749435552156
        },
        {
            "number": -5,
            "real": -10.123950632993203,
            "imag": 18.319384376731062
        },
        {
            "number": 6,
            "real": 0.31596453126066215,
            "imag": -12.893756860681446
        },
        {
            "number": -6,
            "real": -6.822815927622863,
            "imag": -5.738017431071549
        },
        {
            "number": 7,
            "real": -0.5196881070922411,
            "imag": -0.913661709022978
        },
        {
            "number": -7,
            "real": -1.6091298386426383,
            "imag": -4.440759898962053
        },
        {
            "number": 8,
            "real": 0.004243002676636243,
            "imag": 0.005355516086324702
        },
        {
            "number": -8,
            "real": 0.003756997323818234,
            "imag": -0.0003555160858958184
        },
        {
            "number": 9,
            "real": -0.9662596640155965,
            "imag": -2.68539759210363
        },
        {
            "number": -9,
            "real": -0.3158633529782391,
            "imag": -0.5527121207157735
        },
        {
            "number": 10,
            "real": -2.4433716606924643,
            "imag": -2.0780073662962737
        },
        {
            "number": -10,
            "real": 0.10193959913040837,
            "imag": -4.657201711338664
        },
        {
            "number": 11,
            "real": -2.0737772506000653,
            "imag": 3.828573459862302
        },
        {
            "number": -11,
            "real": 0.4553389927421504,
            "imag": -1.0784455699694695
        },
        {
            "number": 12,
            "real": -0.4306360552523415,
            "imag": 0.6681460971410006
        },
        {
            "number": -12,
            "real": -0.45714931153948346,
            "imag": 0.6681460971408834
        },
        {
            "number": 13,
            "real": 0.34526003316149123,
            "imag": -0.8188986453562277
        },
        {
            "number": -13,
            "real": -1.5029030937238648,
            "imag": 2.693845973307562
        },
        {
            "number": 14,
            "real": 0.061854013630049554,
            "imag": -2.3647463142307155
        },
        {
            "number": -14,
            "real": -1.2549278048315584,
            "imag": -1.0495962422085268
        },
        {
            "number": 15,
            "real": -0.11184744997626969,
            "imag": -0.20077810233659704
        },
        {
            "number": -15,
            "real": -0.3517585666156327,
            "imag": -0.9650951959736804
        },
        {
            "number": 16,
            "real": 0.004636300233622659,
            "imag": 0.0011036297100731063
        },
        {
            "number": -16,
            "real": 0.003363699766784606,
            "imag": 0.0038963702902982678
        },
        {
            "number": 17,
            "real": -0.26987501906358663,
            "imag": -0.7501194595098387
        },
        {
            "number": -17,
            "real": -0.08917453211975851,
            "imag": -0.1559302034430758
        },
        {
            "number": 18,
            "real": -0.7530291836849226,
            "imag": -0.6414969528004396
        },
        {
            "number": -18,
            "real": 0.028030803998417453,
            "imag": -1.4384717556836049
        },
        {
            "number": 19,
            "real": -0.6918579102625955,
            "imag": 1.2860305528972178
        },
        {
            "number": -19,
            "real": 0.14868643949179688,
            "imag": -0.3512695675547254
        },
        {
            "number": 20,
            "real": -0.15424620868897512,
            "imag": 0.23972258309188482
        },
        {
            "number": -20,
            "real": -0.17014075353292119,
            "imag": 0.2397225830918603
        },
        {
            "number": 21,
            "real": 0.13395954668467316,
            "imag": -0.3141460214537408
        },
        {
            "number": -21,
            "real": -0.5776535735895394,
            "imag": 1.019509604224509
        },
        {
            "number": 22,
            "real": 0.02461756235906029,
            "imag": -0.960213047163506
        },
        {
            "number": -22,
            "real": -0.5105707374416357,
            "imag": -0.4199888329951027
        },
        {
            "number": 23,
            "real": -0.045775342304973154,
            "imag": -0.09110646606889425
        },
        {
            "number": -23,
            "real": -0.15077329225525998,
            "imag": -0.4057496871096487
        },
        {
            "number": 24,
            "real": 0.006304800353180262,
            "imag": 0.014202579045759361
        },
        {
            "number": -24,
            "real": 0.0016951996472534536,
            "imag": -0.009202579045271803
        },
        {
            "number": 25,
            "real": -0.1232601413437783,
            "imag": -0.3486797030665336
        },
        {
            "number": -25,
            "real": -0.04338870949879792,
            "imag": -0.06705890168833745
        },
        {
            "number": 26,
            "real": -0.35783097965990296,
            "imag": -0.3101066739800024
        },
        {
            "number": -26,
            "real": 0.013770789710584264,
            "imag": -0.6787827070325358
        },
        {
            "number": 27,
            "real": -0.34210516260946583,
            "imag": 0.6474422694916101
        },
        {
            "number": -27,
            "real": 0.0715465573970433,
            "imag": -0.18273292224580173
        },
        {
            "number": 28,
            "real": -0.07506540494463135,
            "imag": 0.12535476229944015
        },
        {
            "number": -28,
            "real": -0.08640427849719684,
            "imag": 0.1253547622992784
        },
        {
            "number": 29,
            "real": 0.07112231652260437,
            "imag": -0.179989349832141
        },
        {
            "number": -29,
            "real": -0.3052461830308692,
            "imag": 0.535822453147577
        },
        {
            "number": 30,
            "real": 0.014965865596865913,
            "imag": -0.5034547930588481
        },
        {
            "number": -30,
            "real": -0.2735010821780982,
            "imag": -0.22270418528827846
        },
        {
            "number": 31,
            "real": -0.027017658537889705,
            "imag": -0.04831164411673325
        },
        {
            "number": -31,
            "real": -0.08078254753857422,
            "imag": -0.2246720035606416
        },
        {
            "number": 32,
            "real": 0.0019458015782654048,
            "imag": 0.002252324225473612
        },
        {
            "number": -32,
            "real": 0.006054198422129287,
            "imag": 0.0027476757748910174
        },
        {
            "number": 33,
            "real": -0.07299081025987972,
            "imag": -0.1961188487794696
        },
        {
            "number": -33,
            "real": -0.023471664127070746,
            "imag": -0.03954152642927433
        },
        {
            "number": 34,
            "real": -0.2084082951139428,
            "imag": -0.1866383991398297
        },
        {
            "number": -34,
            "real": 0.006488337678252021,
            "imag": -0.4029591423813914
        },
        {
            "number": 35,
            "real": -0.2021144337412753,
            "imag": 0.39062947341089155
        },
        {
            "number": -35,
            "real": 0.03917678357387416,
            "imag": -0.10039690607669499
        },
        {
            "number": 36,
            "real": -0.044397820670432214,
            "imag": 0.06854190656418976
        },
        {
            "number": -36,
            "real": -0.05320203065503776,
            "imag": 0.06854190656424208
        },
        {
            "number": 37,
            "real": 0.04136128890370533,
            "imag": -0.10797306083689534
        },
        {
            "number": -37,
            "real": -0.18877103685522417,
            "imag": 0.3308148580231449
        },
        {
            "number": 38,
            "real": 0.00937543423993678,
            "imag": -0.31493567827282953
        },
        {
            "number": -38,
            "real": -0.17015300686477947,
            "imag": -0.14263111561765934
        },
        {
            "number": 39,
            "real": -0.01669488977850736,
            "imag": -0.028150536449001007
        },
        {
            "number": -39,
            "real": -0.05231220306467976,
            "imag": -0.14188897911199513
        },
        {
            "number": 40,
            "real": 0.0033956038250138876,
            "imag": 0.0007266461610483943
        },
        {
            "number": -40,
            "real": 0.00460439617535191,
            "imag": 0.004273353839296917
        },
        {
            "number": 41,
            "real": -0.04631207266526716,
            "imag": -0.12103588284111083
        },
        {
            "number": -41,
            "real": -0.01535811263662118,
            "imag": -0.02934321236915058
        },
        {
            "number": 42,
            "real": -0.13436660580056378,
            "imag": -0.11919351669182704
        },
        {
            "number": -42,
            "real": 0.0033666584613229467,
            "imag": -0.26060616044117124
        },
        {
            "number": 43,
            "real": -0.12911285330010164,
            "imag": 0.2590444874654072
        },
        {
            "number": -43,
            "real": 0.0265274810143436,
            "imag": -0.06623017654401217
        },
        {
            "number": 44,
            "real": -0.02695999608405447,
            "imag": 0.04344340563310162
        },
        {
            "number": -44,
            "real": -0.03414817618560417,
            "imag": 0.04344340563299817
        },
        {
            "number": 45,
            "real": 0.02906003392464751,
            "imag": -0.07329337916596607
        },
        {
            "number": -45,
            "real": -0.12422468053949476,
            "imag": 0.22081544169740547
        },
        {
            "number": 46,
            "real": 0.006579578416392062,
            "imag": -0.21353240289887282
        },
        {
            "number": -46,
            "real": -0.11400773209823822,
            "imag": -0.0939443159418856
        },
        {
            "number": 47,
            "real": -0.009319239973925919,
            "imag": -0.02474420145310141
        },
        {
            "number": -47,
            "real": -0.03410061281098492,
            "imag": -0.0898218654082032
        },
        {
            "number": 48,
            "real": 0.003772347619939498,
            "imag": 0.004957897143894163
        },
        {
            "number": -48,
            "real": 0.004227652380480507,
            "imag": 0.00004210285645814271
        },
        {
            "number": 49,
            "real": -0.035024995382585744,
            "imag": -0.0815078065319616
        },
        {
            "number": -49,
            "real": -0.015025917587992932,
            "imag": -0.015049030426675422
        },
        {
            "number": 50,
            "real": -0.08861033466332002,
            "imag": -0.08364511935245006
        }
    ]
}
